WeiXinNativePay/__init__.py
WeiXinNativePay/version.py
WeiXinNativePay-0.0.1.dist-info/LICENSE
WeiXinNativePay-0.0.1.dist-info/METADATA
WeiXinNativePay-0.0.1.dist-info/WHEEL
WeiXinNativePay-0.0.1.dist-info/top_level.txt
WeiXinNativePay-0.0.1.dist-info/RECORD
