Metadata-Version: 2.1
Name: WeiXinNativePay
Version: 0.0.1
Summary: WeiXinNativePay是基于微信Native支付开发的sdk
Home-page: https://gitee.com/navysummer/WeiXinNativePay
Author: navysummer
Author-email: navysummer@yeah.net
License: UNKNOWN
Platform: python
Classifier: Programming Language :: Python :: 3
Classifier: Programming Language :: Python :: 2
Classifier: Operating System :: OS Independent
Requires-Python: >=2.7
License-File: LICENSE
